form_submit/__init__.py
form_submit/display_form.py
form_submit/handler.py
form_submit/send_email.py
form_submit-0.1.0.dist-info/licenses/LICENSE
form_submit-0.1.0.dist-info/METADATA
form_submit-0.1.0.dist-info/WHEEL
form_submit-0.1.0.dist-info/top_level.txt
form_submit-0.1.0.dist-info/RECORD
