Metadata-Version: 2.4
Name: form_submit
Version: 0.1.0
Summary: A Python package to display an HTML form in Colab, capture submissions, and send data via email.
Home-page: https://github.com/mahdi123-tech/form_submit
Author: Louati Mahdi
Author-email: Louati Mahdi <louatimahdi390@gmail.com>
Project-URL: Homepage, https://github.com/mahdi123-tech/form_submit
Project-URL: Bug Tracker, https://github.com/mahdi123-tech/form_submit/issues
Classifier: Programming Language :: Python :: 3
Classifier: License :: OSI Approved :: MIT License
Classifier: Operating System :: OS Independent
Classifier: Framework :: IPython
Classifier: Topic :: Internet :: WWW/HTTP
Classifier: Topic :: Software Development :: Libraries :: Python Modules
Requires-Python: >=3.7
License-File: LICENSE
Requires-Dist: ipython
Requires-Dist: requests
Requires-Dist: oauth2client
Requires-Dist: google-api-python-client
Dynamic: author
Dynamic: home-page
Dynamic: license-file
Dynamic: requires-python
